makefolio/__init__.py
makefolio/builder.py
makefolio/cli.py
makefolio/content.py
makefolio/server.py
makefolio/utils.py
makefolio/themes/default/static/css/style.css
makefolio/themes/default/static/js/theme.js
makefolio/themes/default/templates/base.html
makefolio/themes/default/templates/education-item.html
makefolio/themes/default/templates/education.html
makefolio/themes/default/templates/experience-item.html
makefolio/themes/default/templates/experience.html
makefolio/themes/default/templates/index.html
makefolio/themes/default/templates/page.html
makefolio/themes/default/templates/project.html
makefolio/themes/default/templates/projects.html
makefolio-0.1.2.dist-info/METADATA
makefolio-0.1.2.dist-info/WHEEL
makefolio-0.1.2.dist-info/entry_points.txt
makefolio-0.1.2.dist-info/top_level.txt
makefolio-0.1.2.dist-info/RECORD
